{"cameraMode":{"drawMode":0,"name":"Shaded","section":"Shading Mode"},"sceneLighting":true,"audioPlay":false,"sceneViewState":{"m_AlwaysRefresh":false,"showFog":true,"showSkybox":true,"showFlares":true,"showImageEffects":true,"showParticleSystems":true,"showVisualEffectGraphs":true,"m_FxEnabled":true},"in2DMode":false,"pivot":{"x":-11.779847145080567,"y":-7.062252044677734,"z":-3.2209079265594484},"rotation":{"x":-0.1484774798154831,"y":0.7805985808372498,"z":-0.20249031484127046,"w":-0.5723790526390076},"size":10.407719612121582,"orthographic":false}